Metadata-Version: 2.1
Name: odoo14-addon-shopinvader
Version: 14.0.5.24.12
Summary: Shopinvader
Home-page: https://github.com/shopinvader/odoo-shopinvader
Author: Akretion
License: AGPL-3
Platform: UNKNOWN
Classifier: Programming Language :: Python
Classifier: Framework :: Odoo
Classifier: Framework :: Odoo :: 14.0
Classifier: License :: OSI Approved :: GNU Affero General Public License v3
Requires-Python: >=3.6
Requires-Dist: cerberus
Requires-Dist: odoo14-addon-base-rest (>=14.0.4.0.0)
Requires-Dist: odoo14-addon-base-sparse-field-list-support
Requires-Dist: odoo14-addon-base-url
Requires-Dist: odoo14-addon-component-event
Requires-Dist: odoo14-addon-jsonifier
Requires-Dist: odoo14-addon-onchange-helper
Requires-Dist: odoo14-addon-queue-job
Requires-Dist: odoo14-addon-sale-discount-display-amount
Requires-Dist: odoo14-addon-server-environment
Requires-Dist: odoo (<14.1dev,>=14.0a)
Requires-Dist: unidecode
